<?xml version="1.0" encoding="UTF-8" standalone="yes" ?>
<AspectLibrary>
    <Name>Metalama.Samples.ChangeTracking (Dirty)</Name>
    <Kind>Sample</Kind>
    <Categories>
        <Category>Component Model</Category>
    </Categories>
    <Author>PostSharp Technologies</Author>
    <Quality>Sample</Quality>
    <License>MIT</License>
    <SourceUrl>https://github.com/postsharp/Metalama.Samples/tree/develop/2023.4/examples/exception-handling/retry</SourceUrl>
    <DocumentationUrl>https://doc.metalama.net/examples/exception-handling/retry</DocumentationUrl>
    <Summary>A series of step-by-step examples on how implement the deep object cloning.
    </Summary>
    <Keywords>
        <Keyword>clone</Keyword>
        <Keyword>deep</Keyword>
        <Keyword>IClonable</Keyword>
    </Keywords>
</AspectLibrary>